{
    "SiteRep": {
        "Wx": {
            "Param": [
                {
                    "name": "G",
                    "units": "mph",
                    "$": "Wind Gust"
                },
                {
                    "name": "T",
                    "units": "C",
                    "$": "Temperature"
                },
                {
                    "name": "V",
                    "units": "m",
                    "$": "Visibility"
                },
                {
                    "name": "D",
                    "units": "compass",
                    "$": "Wind Direction"
                },
                {
                    "name": "S",
                    "units": "mph",
                    "$": "Wind Speed"
                },
                {
                    "name": "W",
                    "units": "",
                    "$": "Weather Type"
                },
                {
                    "name": "P",
                    "units": "hpa",
                    "$": "Pressure"
                },
                {
                    "name": "Pt",
                    "units": "Pa/s",
                    "$": "Pressure Tendency"
                },
                {
                    "name": "Dp",
                    "units": "C",
                    "$": "Dew Point"
                },
                {
                    "name": "H",
                    "units": "%",
                    "$": "Screen Relative Humidity"
                }
            ]
        },
        "DV": {
            "dataDate": "2024-10-05T16:00:00Z",
            "type": "Obs",
            "Location": {
                "i": "3772",
                "lat": "51.479",
                "lon": "-0.449",
                "name": "HEATHROW",
                "country": "ENGLAND",
                "continent": "EUROPE",
                "elevation": "25.0",
                "Period": [
                    {
                        "type": "Day",
                        "value": "2024-10-04Z",
                        "Rep": [
                            {
                                "D": "SSW",
                                "G": "13",
                                "H": "56.1",
                                "P": "1020",
                                "S": "5",
                                "T": "15.2",
                                "V": "55000",
                                "W": "8",
                                "Pt": "F",
                                "Dp": "6.6",
                                "$": "960"
                            },
                            {
                                "D": "SSW",
                                "G": "11",
                                "H": "59.1",
                                "P": "1020",
                                "S": "6",
                                "T": "14.6",
                                "V": "55000",
                                "W": "8",
                                "Pt": "F",
                                "Dp": "6.8",
                                "$": "1020"
                            },
                            {
                                "D": "S",
                                "G": "9",
                                "H": "61.9",
                                "P": "1020",
                                "S": "6",
                                "T": "13.7",
                                "V": "55000",
                                "W": "0",
                                "Pt": "R",
                                "Dp": "6.6",
                                "$": "1080"
                            },
                            {
                                "D": "S",
                                "G": "10",
                                "H": "67.6",
                                "P": "1020",
                                "S": "6",
                                "T": "13.1",
                                "V": "45000",
                                "W": "8",
                                "Pt": "R",
                                "Dp": "7.3",
                                "$": "1140"
                            },
                            {
                                "D": "SSE",
                                "G": "13",
                                "H": "74.2",
                                "P": "1020",
                                "S": "7",
                                "T": "11.6",
                                "V": "45000",
                                "W": "0",
                                "Pt": "S",
                                "Dp": "7.2",
                                "$": "1200"
                            },
                            {
                                "D": "SSE",
                                "G": "11",
                                "H": "79.2",
                                "P": "1020",
                                "S": "6",
                                "T": "10.8",
                                "V": "35000",
                                "W": "8",
                                "Pt": "S",
                                "Dp": "7.4",
                                "$": "1260"
                            },
                            {
                                "D": "SE",
                                "G": "10",
                                "H": "83.1",
                                "P": "1020",
                                "S": "8",
                                "T": "9.4",
                                "V": "28000",
                                "W": "0",
                                "Pt": "F",
                                "Dp": "6.7",
                                "$": "1320"
                            },
                            {
                                "D": "E",
                                "G": "8",
                                "H": "88.9",
                                "P": "1020",
                                "S": "5",
                                "T": "7.8",
                                "V": "24000",
                                "W": "8",
                                "Pt": "F",
                                "Dp": "6.1",
                                "$": "1380"
                            }
                        ]
                    },
                    {
                        "type": "Day",
                        "value": "2024-10-05Z",
                        "Rep": [
                            {
                                "D": "E",
                                "G": "6",
                                "H": "89.5",
                                "P": "1019",
                                "S": "3",
                                "T": "8.4",
                                "V": "35000",
                                "W": "8",
                                "Pt": "F",
                                "Dp": "6.8",
                                "$": "0"
                            },
                            {
                                "D": "ESE",
                                "G": "3",
                                "H": "91.5",
                                "P": "1019",
                                "S": "2",
                                "T": "8.1",
                                "V": "30000",
                                "W": "7",
                                "Pt": "F",
                                "Dp": "6.8",
                                "$": "60"
                            },
                            {
                                "D": "E",
                                "G": "5",
                                "H": "91.4",
                                "P": "1019",
                                "S": "2",
                                "T": "8.3",
                                "V": "29000",
                                "W": "8",
                                "Pt": "F",
                                "Dp": "7.0",
                                "$": "120"
                            },
                            {
                                "D": "E",
                                "G": "6",
                                "H": "90.2",
                                "P": "1018",
                                "S": "3",
                                "T": "9.1",
                                "V": "28000",
                                "W": "8",
                                "Pt": "F",
                                "Dp": "7.6",
                                "$": "180"
                            },
                            {
                                "D": "NNE",
                                "G": "5",
                                "H": "87.2",
                                "P": "1018",
                                "S": "3",
                                "T": "9.5",
                                "V": "24000",
                                "W": "8",
                                "Pt": "F",
                                "Dp": "7.5",
                                "$": "240"
                            },
                            {
                                "D": "ESE",
                                "G": "5",
                                "H": "89.0",
                                "P": "1017",
                                "S": "3",
                                "T": "9.6",
                                "V": "22000",
                                "W": "8",
                                "Pt": "F",
                                "Dp": "7.9",
                                "$": "300"
                            },
                            {
                                "D": "E",
                                "G": "7",
                                "H": "92.1",
                                "P": "1017",
                                "S": "3",
                                "T": "9.2",
                                "V": "21000",
                                "W": "8",
                                "Pt": "F",
                                "Dp": "8.0",
                                "$": "360"
                            },
                            {
                                "D": "ESE",
                                "G": "7",
                                "H": "90.3",
                                "P": "1017",
                                "S": "5",
                                "T": "10.3",
                                "V": "22000",
                                "W": "8",
                                "Pt": "F",
                                "Dp": "8.8",
                                "$": "420"
                            },
                            {
                                "D": "ESE",
                                "G": "10",
                                "H": "85.6",
                                "P": "1017",
                                "S": "7",
                                "T": "11.2",
                                "V": "28000",
                                "W": "8",
                                "Pt": "F",
                                "Dp": "8.9",
                                "$": "480"
                            },
                            {
                                "D": "ESE",
                                "G": "11",
                                "H": "80.1",
                                "P": "1017",
                                "S": "8",
                                "T": "12.5",
                                "V": "30000",
                                "W": "8",
                                "Pt": "F",
                                "Dp": "9.2",
                                "$": "540"
                            },
                            {
                                "D": "SE",
                                "G": "18",
                                "H": "67.7",
                                "P": "1016",
                                "S": "11",
                                "T": "15.7",
                                "V": "45000",
                                "W": "1",
                                "Pt": "F",
                                "Dp": "9.8",
                                "$": "600"
                            },
                            {
                                "D": "SSE",
                                "G": "22",
                                "H": "62.0",
                                "P": "1015",
                                "S": "11",
                                "T": "15.5",
                                "V": "50000",
                                "W": "8",
                                "Pt": "F",
                                "Dp": "8.3",
                                "$": "660"
                            },
                            {
                                "D": "SSE",
                                "G": "21",
                                "H": "58.8",
                                "P": "1015",
                                "S": "15",
                                "T": "16.0",
                                "V": "55000",
                                "W": "7",
                                "Pt": "F",
                                "Dp": "8.0",
                                "$": "720"
                            },
                            {
                                "D": "SE",
                                "G": "21",
                                "H": "55.4",
                                "P": "1014",
                                "S": "15",
                                "T": "16.6",
                                "V": "55000",
                                "W": "7",
                                "Pt": "F",
                                "Dp": "7.7",
                                "$": "780"
                            },
                            {
                                "D": "SE",
                                "G": "21",
                                "H": "51.8",
                                "P": "1013",
                                "S": "14",
                                "T": "17.1",
                                "V": "55000",
                                "W": "8",
                                "Pt": "F",
                                "Dp": "7.2",
                                "$": "840"
                            },
                            {
                                "D": "SE",
                                "G": "21",
                                "H": "50.4",
                                "P": "1012",
                                "S": "14",
                                "T": "17.2",
                                "V": "75000",
                                "W": "8",
                                "Pt": "F",
                                "Dp": "6.9",
                                "$": "900"
                            },
                            {
                                "D": "SE",
                                "G": "23",
                                "H": "52.7",
                                "P": "1011",
                                "S": "13",
                                "T": "16.2",
                                "V": "60000",
                                "W": "1",
                                "Pt": "F",
                                "Dp": "6.6",
                                "$": "960"
                            }
                        ]
                    }
                ]
            }
        }
    }
}