{
    "SiteRep": {
        "Wx": {
            "Param": [
                {
                    "name": "G",
                    "units": "mph",
                    "$": "Wind Gust"
                },
                {
                    "name": "T",
                    "units": "C",
                    "$": "Temperature"
                },
                {
                    "name": "V",
                    "units": "m",
                    "$": "Visibility"
                },
                {
                    "name": "D",
                    "units": "compass",
                    "$": "Wind Direction"
                },
                {
                    "name": "S",
                    "units": "mph",
                    "$": "Wind Speed"
                },
                {
                    "name": "W",
                    "units": "",
                    "$": "Weather Type"
                },
                {
                    "name": "P",
                    "units": "hpa",
                    "$": "Pressure"
                },
                {
                    "name": "Pt",
                    "units": "Pa/s",
                    "$": "Pressure Tendency"
                },
                {
                    "name": "Dp",
                    "units": "C",
                    "$": "Dew Point"
                },
                {
                    "name": "H",
                    "units": "%",
                    "$": "Screen Relative Humidity"
                }
            ]
        },
        "DV": {
            "dataDate": "2025-11-14T16:00:00Z",
            "type": "Obs",
            "Location": {
                "i": "3772",
                "lat": "51.479",
                "lon": "-0.449",
                "name": "HEATHROW",
                "country": "ENGLAND",
                "continent": "EUROPE",
                "elevation": "25.0",
                "Period": [
                    {
                        "type": "Day",
                        "value": "2025-11-13Z",
                        "Rep": [
                            {
                                "D": "E",
                                "G": "10",
                                "H": "74.0",
                                "P": "1007",
                                "S": "5",
                                "T": "15.6",
                                "V": "30000",
                                "W": "8",
                                "Pt": "F",
                                "Dp": "11.0",
                                "$": "960"
                            },
                            {
                                "D": "E",
                                "G": "8",
                                "H": "77.9",
                                "P": "1007",
                                "S": "5",
                                "T": "14.9",
                                "V": "30000",
                                "W": "8",
                                "Pt": "F",
                                "Dp": "11.1",
                                "$": "1020"
                            },
                            {
                                "D": "ESE",
                                "G": "10",
                                "H": "86.6",
                                "P": "1006",
                                "S": "7",
                                "T": "14.1",
                                "V": "29000",
                                "W": "12",
                                "Pt": "F",
                                "Dp": "11.9",
                                "$": "1080"
                            },
                            {
                                "D": "SE",
                                "G": "11",
                                "H": "90.6",
                                "P": "1007",
                                "S": "7",
                                "T": "13.8",
                                "V": "11000",
                                "W": "12",
                                "Pt": "F",
                                "Dp": "12.3",
                                "$": "1140"
                            },
                            {
                                "D": "ESE",
                                "G": "11",
                                "H": "95.5",
                                "P": "1007",
                                "S": "8",
                                "T": "13.7",
                                "V": "4200",
                                "W": "12",
                                "Pt": "R",
                                "Dp": "13.0",
                                "$": "1200"
                            },
                            {
                                "D": "E",
                                "G": "11",
                                "H": "97.4",
                                "P": "1006",
                                "S": "5",
                                "T": "13.5",
                                "V": "7000",
                                "W": "12",
                                "Pt": "R",
                                "Dp": "13.1",
                                "$": "1260"
                            },
                            {
                                "D": "ENE",
                                "G": "10",
                                "H": "96.8",
                                "P": "1005",
                                "S": "7",
                                "T": "13.6",
                                "V": "13000",
                                "W": "12",
                                "Pt": "F",
                                "Dp": "13.1",
                                "$": "1320"
                            },
                            {
                                "D": "NE",
                                "G": "11",
                                "H": "96.8",
                                "P": "1005",
                                "S": "7",
                                "T": "13.6",
                                "V": "8000",
                                "W": "12",
                                "Pt": "F",
                                "Dp": "13.1",
                                "$": "1380"
                            }
                        ]
                    },
                    {
                        "type": "Day",
                        "value": "2025-11-14Z",
                        "Rep": [
                            {
                                "D": "ENE",
                                "G": "14",
                                "H": "96.1",
                                "P": "1005",
                                "S": "8",
                                "T": "13.6",
                                "V": "10000",
                                "W": "12",
                                "Pt": "F",
                                "Dp": "13.0",
                                "$": "0"
                            },
                            {
                                "D": "ENE",
                                "G": "14",
                                "H": "96.1",
                                "P": "1004",
                                "S": "9",
                                "T": "13.5",
                                "V": "9000",
                                "W": "8",
                                "Pt": "F",
                                "Dp": "12.9",
                                "$": "60"
                            },
                            {
                                "D": "ENE",
                                "G": "16",
                                "H": "95.5",
                                "P": "1004",
                                "S": "9",
                                "T": "13.5",
                                "V": "7000",
                                "W": "8",
                                "Pt": "F",
                                "Dp": "12.8",
                                "$": "120"
                            },
                            {
                                "D": "ENE",
                                "G": "18",
                                "H": "94.9",
                                "P": "1003",
                                "S": "9",
                                "T": "13.4",
                                "V": "7000",
                                "W": "8",
                                "Pt": "F",
                                "Dp": "12.6",
                                "$": "180"
                            },
                            {
                                "D": "E",
                                "G": "14",
                                "H": "94.9",
                                "P": "1002",
                                "S": "9",
                                "T": "13.4",
                                "V": "7000",
                                "W": "12",
                                "Pt": "F",
                                "Dp": "12.6",
                                "$": "240"
                            },
                            {
                                "D": "E",
                                "G": "14",
                                "H": "96.2",
                                "P": "1001",
                                "S": "9",
                                "T": "13.1",
                                "V": "4100",
                                "W": "12",
                                "Pt": "F",
                                "Dp": "12.5",
                                "$": "300"
                            },
                            {
                                "D": "E",
                                "G": "15",
                                "H": "96.8",
                                "P": "1001",
                                "S": "8",
                                "T": "13.0",
                                "V": "5000",
                                "W": "12",
                                "Pt": "F",
                                "Dp": "12.5",
                                "$": "360"
                            },
                            {
                                "D": "ENE",
                                "G": "11",
                                "H": "96.8",
                                "P": "1001",
                                "S": "6",
                                "T": "13.2",
                                "W": "12",
                                "Pt": "F",
                                "Dp": "12.7",
                                "$": "420"
                            },
                            {
                                "D": "E",
                                "G": "9",
                                "H": "96.8",
                                "P": "1001",
                                "S": "5",
                                "T": "13.3",
                                "V": "6000",
                                "W": "8",
                                "Pt": "F",
                                "Dp": "12.8",
                                "$": "480"
                            },
                            {
                                "D": "E",
                                "G": "10",
                                "H": "96.2",
                                "P": "1001",
                                "S": "7",
                                "T": "13.5",
                                "V": "7000",
                                "W": "8",
                                "Pt": "F",
                                "Dp": "12.9",
                                "$": "540"
                            },
                            {
                                "D": "ENE",
                                "G": "11",
                                "H": "96.8",
                                "P": "1001",
                                "S": "7",
                                "T": "13.6",
                                "V": "3200",
                                "W": "12",
                                "Pt": "F",
                                "Dp": "13.1",
                                "$": "600"
                            },
                            {
                                "D": "ENE",
                                "G": "11",
                                "H": "97.5",
                                "P": "1000",
                                "S": "7",
                                "T": "13.8",
                                "V": "5000",
                                "W": "12",
                                "Pt": "F",
                                "Dp": "13.4",
                                "$": "660"
                            },
                            {
                                "D": "E",
                                "G": "11",
                                "H": "97.5",
                                "P": "1000",
                                "S": "5",
                                "T": "13.8",
                                "V": "5000",
                                "W": "12",
                                "Pt": "F",
                                "Dp": "13.4",
                                "$": "720"
                            },
                            {
                                "D": "E",
                                "G": "13",
                                "H": "97.4",
                                "P": "999",
                                "S": "8",
                                "T": "14.0",
                                "V": "9000",
                                "W": "11",
                                "Pt": "F",
                                "Dp": "13.6",
                                "$": "780"
                            },
                            {
                                "D": "E",
                                "G": "13",
                                "H": "98.1",
                                "P": "999",
                                "S": "8",
                                "T": "14.0",
                                "V": "4000",
                                "W": "12",
                                "Pt": "F",
                                "Dp": "13.7",
                                "$": "840"
                            },
                            {
                                "D": "ENE",
                                "G": "15",
                                "H": "97.5",
                                "P": "998",
                                "S": "8",
                                "T": "14.3",
                                "V": "16000",
                                "W": "8",
                                "Pt": "F",
                                "Dp": "13.9",
                                "$": "900"
                            },
                            {
                                "D": "E",
                                "G": "14",
                                "H": "95.6",
                                "P": "998",
                                "S": "8",
                                "T": "14.3",
                                "V": "16000",
                                "W": "8",
                                "Pt": "F",
                                "Dp": "13.6",
                                "$": "960"
                            }
                        ]
                    }
                ]
            }
        }
    }
}