{
    "SiteRep": {
        "Wx": {
            "Param": [
                {
                    "name": "G",
                    "units": "mph",
                    "$": "Wind Gust"
                },
                {
                    "name": "T",
                    "units": "C",
                    "$": "Temperature"
                },
                {
                    "name": "V",
                    "units": "m",
                    "$": "Visibility"
                },
                {
                    "name": "D",
                    "units": "compass",
                    "$": "Wind Direction"
                },
                {
                    "name": "S",
                    "units": "mph",
                    "$": "Wind Speed"
                },
                {
                    "name": "W",
                    "units": "",
                    "$": "Weather Type"
                },
                {
                    "name": "P",
                    "units": "hpa",
                    "$": "Pressure"
                },
                {
                    "name": "Pt",
                    "units": "Pa/s",
                    "$": "Pressure Tendency"
                },
                {
                    "name": "Dp",
                    "units": "C",
                    "$": "Dew Point"
                },
                {
                    "name": "H",
                    "units": "%",
                    "$": "Screen Relative Humidity"
                }
            ]
        },
        "DV": {
            "dataDate": "2024-11-25T16:00:00Z",
            "type": "Obs",
            "Location": {
                "i": "3772",
                "lat": "51.479",
                "lon": "-0.449",
                "name": "HEATHROW",
                "country": "ENGLAND",
                "continent": "EUROPE",
                "elevation": "25.0",
                "Period": [
                    {
                        "type": "Day",
                        "value": "2024-11-24Z",
                        "Rep": [
                            {
                                "D": "S",
                                "G": "48",
                                "H": "73.3",
                                "P": "993",
                                "S": "22",
                                "T": "16.2",
                                "V": "19000",
                                "W": "12",
                                "Pt": "F",
                                "Dp": "11.4",
                                "$": "960"
                            },
                            {
                                "D": "S",
                                "G": "38",
                                "H": "69.1",
                                "P": "993",
                                "S": "22",
                                "T": "16.5",
                                "V": "23000",
                                "W": "8",
                                "Pt": "F",
                                "Dp": "10.8",
                                "$": "1020"
                            },
                            {
                                "D": "S",
                                "G": "39",
                                "H": "71.9",
                                "P": "993",
                                "S": "25",
                                "T": "16.1",
                                "V": "19000",
                                "W": "12",
                                "Pt": "F",
                                "Dp": "11.0",
                                "$": "1080"
                            },
                            {
                                "D": "S",
                                "G": "38",
                                "H": "76.6",
                                "P": "993",
                                "S": "22",
                                "T": "15.4",
                                "V": "14000",
                                "W": "12",
                                "Pt": "F",
                                "Dp": "11.3",
                                "$": "1140"
                            },
                            {
                                "D": "S",
                                "G": "37",
                                "H": "81.8",
                                "P": "993",
                                "S": "21",
                                "T": "14.7",
                                "V": "10000",
                                "W": "12",
                                "Pt": "F",
                                "Dp": "11.6",
                                "$": "1200"
                            },
                            {
                                "D": "SW",
                                "G": "41",
                                "H": "91.3",
                                "P": "993",
                                "S": "21",
                                "T": "13.8",
                                "V": "1600",
                                "W": "12",
                                "Pt": "R",
                                "Dp": "12.4",
                                "$": "1260"
                            },
                            {
                                "D": "SW",
                                "G": "30",
                                "H": "94.3",
                                "P": "994",
                                "S": "17",
                                "T": "13.0",
                                "V": "4600",
                                "W": "12",
                                "Pt": "R",
                                "Dp": "12.1",
                                "$": "1320"
                            },
                            {
                                "D": "WSW",
                                "G": "36",
                                "H": "94.3",
                                "P": "995",
                                "S": "11",
                                "T": "11.5",
                                "V": "4700",
                                "W": "12",
                                "Pt": "R",
                                "Dp": "10.6",
                                "$": "1380"
                            }
                        ]
                    },
                    {
                        "type": "Day",
                        "value": "2024-11-25Z",
                        "Rep": [
                            {
                                "D": "WSW",
                                "G": "26",
                                "H": "91.0",
                                "P": "995",
                                "S": "13",
                                "T": "9.7",
                                "V": "6000",
                                "W": "12",
                                "Pt": "R",
                                "Dp": "8.3",
                                "$": "0"
                            },
                            {
                                "D": "SW",
                                "G": "18",
                                "H": "92.1",
                                "P": "996",
                                "S": "11",
                                "T": "9.6",
                                "V": "8000",
                                "W": "12",
                                "Pt": "R",
                                "Dp": "8.4",
                                "$": "60"
                            },
                            {
                                "D": "S",
                                "G": "16",
                                "H": "90.4",
                                "P": "995",
                                "S": "9",
                                "T": "9.9",
                                "V": "40000",
                                "W": "12",
                                "Pt": "R",
                                "Dp": "8.4",
                                "$": "120"
                            },
                            {
                                "D": "S",
                                "G": "17",
                                "H": "90.4",
                                "P": "995",
                                "S": "11",
                                "T": "9.9",
                                "V": "30000",
                                "W": "8",
                                "Pt": "F",
                                "Dp": "8.4",
                                "$": "180"
                            },
                            {
                                "D": "S",
                                "G": "19",
                                "H": "91.6",
                                "P": "995",
                                "S": "11",
                                "T": "10.0",
                                "V": "26000",
                                "W": "8",
                                "Pt": "F",
                                "Dp": "8.7",
                                "$": "240"
                            },
                            {
                                "D": "S",
                                "G": "18",
                                "H": "91.6",
                                "P": "996",
                                "S": "10",
                                "T": "10.1",
                                "V": "23000",
                                "W": "8",
                                "Pt": "R",
                                "Dp": "8.8",
                                "$": "300"
                            },
                            {
                                "D": "S",
                                "G": "15",
                                "H": "92.8",
                                "P": "996",
                                "S": "9",
                                "T": "10.1",
                                "V": "18000",
                                "W": "8",
                                "Pt": "R",
                                "Dp": "9.0",
                                "$": "360"
                            },
                            {
                                "D": "SSW",
                                "G": "16",
                                "H": "89.2",
                                "P": "996",
                                "S": "10",
                                "T": "10.6",
                                "V": "17000",
                                "W": "8",
                                "Pt": "R",
                                "Dp": "8.9",
                                "$": "420"
                            },
                            {
                                "D": "SSW",
                                "G": "17",
                                "H": "88.0",
                                "P": "997",
                                "S": "8",
                                "T": "10.5",
                                "V": "16000",
                                "W": "8",
                                "Pt": "R",
                                "Dp": "8.6",
                                "$": "480"
                            },
                            {
                                "D": "SW",
                                "G": "16",
                                "H": "83.8",
                                "P": "999",
                                "S": "13",
                                "T": "10.4",
                                "V": "21000",
                                "W": "3",
                                "Pt": "R",
                                "Dp": "7.8",
                                "$": "540"
                            },
                            {
                                "D": "SW",
                                "G": "22",
                                "H": "81.1",
                                "P": "1000",
                                "S": "14",
                                "T": "10.5",
                                "V": "25000",
                                "W": "1",
                                "Pt": "R",
                                "Dp": "7.4",
                                "$": "600"
                            },
                            {
                                "D": "WSW",
                                "G": "21",
                                "H": "77.3",
                                "P": "1000",
                                "S": "15",
                                "T": "10.6",
                                "V": "28000",
                                "W": "1",
                                "Pt": "R",
                                "Dp": "6.8",
                                "$": "660"
                            },
                            {
                                "D": "WSW",
                                "G": "28",
                                "H": "69.0",
                                "P": "1001",
                                "S": "18",
                                "T": "11.8",
                                "V": "30000",
                                "W": "7",
                                "Pt": "R",
                                "Dp": "6.3",
                                "$": "720"
                            },
                            {
                                "D": "WSW",
                                "G": "28",
                                "H": "63.5",
                                "P": "1001",
                                "S": "16",
                                "T": "12.1",
                                "V": "30000",
                                "W": "7",
                                "Pt": "R",
                                "Dp": "5.4",
                                "$": "780"
                            },
                            {
                                "D": "WSW",
                                "G": "28",
                                "H": "61.6",
                                "P": "1002",
                                "S": "19",
                                "T": "11.1",
                                "V": "30000",
                                "W": "3",
                                "Pt": "R",
                                "Dp": "4.0",
                                "$": "840"
                            },
                            {
                                "D": "WSW",
                                "G": "34",
                                "H": "57.7",
                                "P": "1003",
                                "S": "19",
                                "T": "11.2",
                                "V": "35000",
                                "W": "3",
                                "Pt": "R",
                                "Dp": "3.2",
                                "$": "900"
                            },
                            {
                                "D": "SW",
                                "G": "29",
                                "H": "63.0",
                                "P": "1004",
                                "S": "16",
                                "T": "10.1",
                                "V": "40000",
                                "W": "3",
                                "Pt": "R",
                                "Dp": "3.4",
                                "$": "960"
                            }
                        ]
                    }
                ]
            }
        }
    }
}